zxsecurity/__init__.py
zxsecurity/authorization.py
zxsecurity/initializer.py
zxsecurity_flask-0.1.0.dist-info/LICENSE
zxsecurity_flask-0.1.0.dist-info/METADATA
zxsecurity_flask-0.1.0.dist-info/WHEEL
zxsecurity_flask-0.1.0.dist-info/top_level.txt
zxsecurity_flask-0.1.0.dist-info/RECORD
