Metadata-Version: 2.1
Name: zxsecurity-flask
Version: 0.1.0
Summary: A Flask-adapted version of ZXsecurity in Python
Author: ZXstudios
Requires-Python: >=3.7
License-File: LICENSE
Requires-Dist: psutil >=5.9.8
Requires-Dist: requests >=2.31.0
Requires-Dist: flask
Requires-Dist: python-dateutil >=2.8.2
Requires-Dist: cryptography
